Workbook

Sheet ЗАДАНИЕ
C1: Магистрантам в учебном году 2025 в имени файла ставить 4.506М-3-МНК-Фамилия или 4.506Мз-3
A3: Номера вариантов индивидуальных расчетных работ
H4: Нужно:
B32: Номера вариантов для группы 4.606Мз-3
A33: № вар
A34: 23
A35: 24
A36: 25
A37: 26
A38: 27
A39: 28
A40: 29
A41: 30
A42: 31
A43: 32
A44: 33
A45: 34
A46: 35

Sheet ОЦЕНКА МНК
B1: Таблица. Стоимости 1 кв. м. и бальная характеристика объектов - аналогов | J1: Скидка= | K1: 0.05 | M1: Варианты индивидуальных заданий
A2: Аналоги | B2: Цена предложения за 1 кв.м | C2: Цена с учетом скидки | D2: Площадь кв.м | E2: Оживл улицы | F2: Этаж располож | G2: Число выходов | H2: Состояние объекта | I2: Формула оценки | J2: Е | K2: Е*Е | L2: W | M2: № п/п | N2: Скидка= Ячейка К1 | O2: Площадь Объекта. Ячейка D23
A3: Объект № 1 | B3: 73614.5 | C3: =(1-$K$1)*B3 -> 69933.775 | D3: 240 | E3: 2 | F3: 2 | G3: 3 | H3: 2 | I3: =$A$27+SUMPRODUCT(D3:H3,$B$27:$F$27) -> 77922.121 | J3: =(C3-I3)*L3 -> -7988.3465 | K3: =J3*J3 -> 63813680 | L3: 1 | M3: 1 | N3: 0 | O3: 150
A4: Объект № 2 | B4: 54683.5 | C4: =(1-$K$1)*B4 -> 51949.325 | D4: 350 | E4: 2 | F4: 1 | G4: 2 | H4: 2 | I4: =$A$27+SUMPRODUCT(D4:H4,$B$27:$F$27) -> 38737.205 | J4: =(C4-I4)*L4 -> 0 | K4: =J4*J4 -> 0 | L4: 0 | M4: 2 | N4: 0.05 | O4: 150
A5: Объект № 3 | B5: 71229.75 | C5: =(1-$K$1)*B5 -> 67668.262 | D5: 62 | E5: 1 | F5: 2 | G5: 1 | H5: 1 | I5: =$A$27+SUMPRODUCT(D5:H5,$B$27:$F$27) -> 72949.127 | J5: =(C5-I5)*L5 -> -5280.8642 | K5: =J5*J5 -> 27887527 | L5: 1 | M5: 3 | N5: 0.1 | O5: 150
A6: Объект № 4 | B6: 93074.75 | C6: =(1-$K$1)*B6 -> 88421.012 | D6: 87 | E6: 1 | F6: 1 | G6: 2 | H6: 3 | I6: =$A$27+SUMPRODUCT(D6:H6,$B$27:$F$27) -> 87810.98 | J6: =(C6-I6)*L6 -> 610.03238 | K6: =J6*J6 -> 372139.5 | L6: 1 | M6: 4 | N6: 0.15 | O6: 150
A7: Объект № 5 | B7: 107686.5 | C7: =(1-$K$1)*B7 -> 102302.17 | D7: 67 | E7: 1 | F7: 2 | G7: 3 | H7: 1 | I7: =$A$27+SUMPRODUCT(D7:H7,$B$27:$F$27) -> 97847.894 | J7: =(C7-I7)*L7 -> 4454.2813 | K7: =J7*J7 -> 19840622 | L7: 1 | M7: 5 | N7: 0 | O7: 200
A8: Объект № 6 | B8: 82500 | C8: =(1-$K$1)*B8 -> 78375 | D8: 145 | E8: 2 | F8: 2 | G8: 3 | H8: 2 | I8: =$A$27+SUMPRODUCT(D8:H8,$B$27:$F$27) -> 80835.91 | J8: =(C8-I8)*L8 -> -2460.91 | K8: =J8*J8 -> 6056078.1 | L8: 1 | M8: 6 | N8: 0.05 | O8: 200
A9: Объект № 7 | B9: 60897.75 | C9: =(1-$K$1)*B9 -> 57852.862 | D9: 110 | E9: 2 | F9: 2 | G9: 3 | H9: 2 | I9: =$A$27+SUMPRODUCT(D9:H9,$B$27:$F$27) -> 81909.411 | J9: =(C9-I9)*L9 -> 0 | K9: =J9*J9 -> 0 | L9: 0 | M9: 7 | N9: 0.1 | O9: 200
A10: Объект № 8 | B10: 92751.25 | C10: =(1-$K$1)*B10 -> 88113.688 | D10: 184 | E10: 1 | F10: 2 | G10: 3 | H10: 2 | I10: =$A$27+SUMPRODUCT(D10:H10,$B$27:$F$27) -> 107453.12 | J10: =(C10-I10)*L10 -> 0 | K10: =J10*J10 -> 0 | L10: 0 | M10: 8 | N10: 0.15 | O10: 200
A11: Объект № 9 | B11: 27605.75 | C11: =(1-$K$1)*B11 -> 26225.462 | D11: 520 | E11: 2 | F11: 2 | G11: 1 | H11: 1 | I11: =$A$27+SUMPRODUCT(D11:H11,$B$27:$F$27) -> 31088.203 | J11: =(C11-I11)*L11 -> -4862.7408 | K11: =J11*J11 -> 23646248 | L11: 1 | M11: 9 | N11: 0 | O11: 250
A12: Объект № 10 | B12: 69933.25 | C12: =(1-$K$1)*B12 -> 66436.587 | D12: 450 | E12: 1 | F12: 1 | G12: 2 | H12: 2 | I12: =$A$27+SUMPRODUCT(D12:H12,$B$27:$F$27) -> 63483.455 | J12: =(C12-I12)*L12 -> 2953.1323 | K12: =J12*J12 -> 8720990.6 | L12: 1 | M12: 10 | N12: 0.05 | O12: 250
A13: Объект № 11 | B13: 76838.25 | C13: =(1-$K$1)*B13 -> 72996.337 | D13: 68 | E13: 2 | F13: 2 | G13: 2 | H13: 2 | I13: =$A$27+SUMPRODUCT(D13:H13,$B$27:$F$27) -> 70671.55 | J13: =(C13-I13)*L13 -> 2324.7874 | K13: =J13*J13 -> 5404636.3 | L13: 1 | M13: 11 | N13: 0.1 | O13: 250
A14: Объект № 12 | B14: 81250 | C14: =(1-$K$1)*B14 -> 77187.5 | D14: 40 | E14: 2 | F14: 2 | G14: 2 | H14: 3 | I14: =$A$27+SUMPRODUCT(D14:H14,$B$27:$F$27) -> 84724.137 | J14: =(C14-I14)*L14 -> -7536.6366 | K14: =J14*J14 -> 56800892 | L14: 1 | M14: 12 | N14: 0.15 | O14: 300
... A22: Объект № 20 | B22: 59121.5 | C22: =(1-$K$1)*B22 -> 56165.425 | D22: 74 | E22: 2 | F22: 1 | G22: 3 | H22: 2 | I22: =$A$27+SUMPRODUCT(D22:H22,$B$27:$F$27) -> 59728.59 | J22: =(C22-I22)*L22 -> -3563.1649 | K22: =J22*J22 -> 12696144 | L22: 1 | M22: 20 | N22: 0.15 | O22: 400
A23: Объект Оценки | D23: 500 | E23: 2 | F23: 2 | G23: 2 | H23: 2 | I23: =$A$27+SUMPRODUCT(D23:H23,$B$27:$F$27) -> 57421.48 | J23: =AVERAGE(J3:J22) -> -3.6843471e-05 | K23: =AVERAGE(K3:K22) -> 18421412 | M23: 21 | N23: 0 | O23: 450
M24: 22 | N24: 0.05 | O24: 450
M25: 23 | N25: 0.1 | O25: 450
A26: A0 | B26: A1 | C26: A2 | D26: A3 | E26: A4 | F26: A5 | H26: Множ R2 | M26: 24 | N26: 0.15 | O26: 450
A27: 30374.318 | B27: -30.671458 | C27: -27813.396 | D27: 23284.994 | E27: 12526.062 | F27: 13193.786 | H27: =1-(G30/G32) -> 0.94270246 | M27: 25 | N27: 0 | O27: 500
B28: ТОЧНЫЕ ЗНАЧЕНИЯ | M28: 26 | N28: 0.05 | O28: 500
A29: 40125.792 | B29: -32.184711 | C29: -23146.17 | D29: 17861.003 | E29: 11069.833 | F29: 12782.629 | M29: 27 | N29: 0.1 | O29: 500
G30: =VAR(J3:J22) -> 19390960 | M30: 28 | N30: 0.15 | O30: 500
M31: 29 | N31: 0 | O31: 550
G32: =VAR(C3:C22) -> 3.3842572e+08 | M32: 30 | N32: 0.05 | O32: 550
M33: 31 | N33: 0.1 | O33: 550
M34: 32 | N34: 0.15 | O34: 550
M35: 33 | N35: 0.05 | O35: 600
M36: 34 | N36: 0.1 | O36: 600
M37: 35 | N37: 0.15 | O37: 600

Sheet АНАЛИЗ
B14: Анализ результатов построения модели прогноза рыночной стоимости объекта оценки
B16: Верификация модели | E16: Первый метод | J16: Верификация модели | M16: Второй метод
C17: Оценка дисперсии ошибки е= | G17: ='ОЦЕНКА МНК'!G30 -> 19390960 | I17: Оценка дисперсии ошибки е= | M17: =G17 -> 19390960
C18: Оценка СКО ошибки е= | G18: =SQRT(G17) -> 4403.5168 | I18: Оценка дисперсии выходной перем у= | M18: ='ОЦЕНКА МНК'!G32 -> 3.3842572e+08
C19: Оценка Абсоютной ошибки е= | G19: =1.96*G18 -> 8630.893 | I19: Квадрат множ. коэфф. корреляции R2= | M19: =1-M17/M18 -> 0.94270246 | N19: =IF(M19<0.9,"Высокая","Оч. выс") -> Оч. выс
I20: ВЫВОД: формула оценки работоспособна? Да-1 нет-0 | N20: 1
E22: Итоговый результат | I22: Оценка стоимости= | K22: ='ОЦЕНКА МНК'!I23/1000 -> 57.42148 | L22: тыс. руб. за 1 кв. м оцениваемого объекта
I23: Ошибка, АБС | K23: =G19/1000 -> 8.630893 | L23: тыс руб
I24: Ошибка,% | K24: =K23/K22 -> 0.15030774 | L24: %
I25: Оценка стоимости объекта | K25: ='ОЦЕНКА МНК'!$D$23*K22/1000 -> 28.71074 | L25: млн. руб.
I26: Ошибка, АБС | K26: ='ОЦЕНКА МНК'!$D$23*K23/1000 -> 4.3154465 | L26: млн. руб.
K28: ДА или НЕТ?
E29: ВЫВОД: формула оценки работоспособна? ДА или НЕТ | J29: ОТВЕТ: | K29: ДА
K31: ДА или НЕТ?
E32: ВЫВОД: Можно ли по имеющимся данным оценить адекватность модели? ДА или НЕТ | J32: ОТВЕТ: | K32: ДА

Sheet ТЕСТ ПОИСК-РЕШЕНИЯ
C1: Задание для освоения инструмента Excel "Поиск решения"
B3: Простая задача, которую можно решить усно.
B4: Найти 10 чисел сумму которых максимальна, а их значения не превышают заданные.
B5: Решить устно в таблице 1 | F5: Решить инструментом "Поиск решения" в таблице 2
B6: Исходные условия | D6: Таб. 1 | G6: Исходные условия | I6: Таб. 2
B7: № п/п | C7: Граница | D7: Искомые | G7: № п/п | H7: Граница | I7: Искомые
B8: 1 | C8: 10 | D8: 1 | G8: 1 | H8: 10 | I8: 10
B9: 2 | C9: 20 | D9: 2 | G9: 2 | H9: 20 | I9: 20
B10: 3 | C10: 30 | D10: 3 | G10: 3 | H10: 30 | I10: 30
B11: 4 | C11: 40 | D11: 4 | G11: 4 | H11: 40 | I11: 40
B12: 5 | C12: 50 | D12: 5 | G12: 5 | H12: 50 | I12: 50
B13: 6 | C13: 60 | D13: 6 | G13: 6 | H13: 60 | I13: 60
B14: 7 | C14: 70 | D14: 7 | G14: 7 | H14: 70 | I14: 70
B15: 8 | C15: 80 | D15: 8 | G15: 8 | H15: 80 | I15: 80
B16: 9 | C16: 90 | D16: 9 | G16: 9 | H16: 90 | I16: 90
B17: 10 | C17: 100 | D17: 10 | G17: 10 | H17: 100 | I17: 100
D18: =SUM(D8:D17) -> 55 | I18: =SUM(I8:I17) -> 550
B20: Порядок решения (учитываем, что правильное решение: ИСКОМЫЕ ЧИСЛА = ГРАНИЦА)
B21: Действие 1 | D21: Актуализировать на своем компьютере инструмент "ПОИСК РЕШЕНИЯ"
B22: Последоватеьность действий: Файл | G22: параметры | I22: надстройки | K22: перейти | M22: посик решения ОК
C23: Инструкция в картинках (скопированы в файлах к лекции 4)
C24: http://www.excelworld.ru/publ/hacks/tools/solver/27-1-0-122
B26: Действие 2 | D26: Запускаем на этом листе Поиск решения (ВСЕ ЗАПРОГОРАММИРОВАНО!)
I28: Действие 3
I29: Кнопки "Найти решение"
I30: Контролировать процесс и
I31: "СОХРАНИТЬ решение"
I33: Примечание: В этой версии автор
I34: СОХРАНИЛ ИСХОДНЫЕ ДАННЫЕ
